fridaDownloader/__init__.py
fridaDownloader/main.py
fridaDownloader-1.3.0.dist-info/LICENSE
fridaDownloader-1.3.0.dist-info/METADATA
fridaDownloader-1.3.0.dist-info/WHEEL
fridaDownloader-1.3.0.dist-info/entry_points.txt
fridaDownloader-1.3.0.dist-info/top_level.txt
fridaDownloader-1.3.0.dist-info/RECORD
