Metadata-Version: 2.2
Name: fridaDownloader
Version: 1.3.0
Summary: fridaDownloader is a command-line tool that streamlines downloading the Frida Gadget or Server for Android, enabling developers and security researchers to quickly access the components needed for dynamic instrumentation.
Home-page: https://github.com/mateofumis/fridaDownloader
Author: Mateo Fumis
Author-email: mateofumis1@gmail.com
Classifier: Programming Language :: Python :: 3
Classifier: License :: OSI Approved :: Apache Software License
Classifier: Operating System :: OS Independent
Requires-Python: >=3.6
License-File: LICENSE
Requires-Dist: requests==2.32.3
Dynamic: author
Dynamic: author-email
Dynamic: classifier
Dynamic: description
Dynamic: description-content-type
Dynamic: home-page
Dynamic: requires-dist
Dynamic: requires-python
Dynamic: summary
